arabic_conjugator-0.1.0.dist-info/licenses/LICENSE
arabic_conjugator_hmolavi/__init__.py
arabic_conjugator_hmolavi/core.py
arabic_conjugator-0.1.0.dist-info/METADATA
arabic_conjugator-0.1.0.dist-info/WHEEL
arabic_conjugator-0.1.0.dist-info/top_level.txt
arabic_conjugator-0.1.0.dist-info/RECORD
