Metadata-Version: 2.4
Name: arabic-conjugator
Version: 0.1.0
Summary: Utilities for Arabic verb root parsing and conjugation.
Author: hmolavi
License-Expression: MIT
Project-URL: Source, https://github.com/hmolavi/ArabicConjugator
Keywords: arabic,conjugation,triliteral
License-File: LICENSE
Dynamic: license-file
